README.md
setup.py
prasadi/__init__.py
prasadi.egg-info/PKG-INFO
prasadi.egg-info/SOURCES.txt
prasadi.egg-info/dependency_links.txt
prasadi.egg-info/top_level.txt
prasadi/example_dags/__init__.py
prasadi/example_dags/sample-dag.py
prasadi/hooks/__init__.py
prasadi/hooks/sample_hook.py
prasadi/operators/__init__.py
prasadi/operators/sample_operator.py
prasadi/sensors/__init__.py
prasadi/sensors/sample_sensor.py