Metadata-Version: 2.1
Name: prasadi
Version: 0.0.5
Summary: A sample provider package built by Astronomer.
Home-page: http://astronomer.io/
Author: prasadi
Author-email: prasadi.jayakodi@novigi.com.au
License: Apache License 2.0
Platform: UNKNOWN
Requires-Python: >=2.7
